taipan/__init__.py
taipan/__main__.py
taipan/analyzer.py
taipan/ast.py
taipan/compiler.py
taipan/emitter.py
taipan/exceptions.py
taipan/lexer.py
taipan/location.py
taipan/parser.py
taipan/symbol_table.py
taipan/templates/__init__.py
taipan/templates/functions/__init__.py
taipan/templates/functions/input.j2
taipan/templates/functions/print.j2
taipan_lang-0.2.0.dist-info/LICENCE.md
taipan_lang-0.2.0.dist-info/METADATA
taipan_lang-0.2.0.dist-info/WHEEL
taipan_lang-0.2.0.dist-info/entry_points.txt
taipan_lang-0.2.0.dist-info/RECORD
