Metadata-Version: 2.1
Name: taipan-lang
Version: 0.2.0
Summary: Taipan is a simple imperative programming language.
Home-page: https://github.com/TheoGuerin64/taipan
License: MIT
Author: Theo Guerin
Requires-Python: >=3.12,<4.0
Classifier: License :: OSI Approved :: MIT License
Classifier: Programming Language :: Python :: 3
Classifier: Programming Language :: Python :: 3.12
Requires-Dist: click (>=8.1,<9.0)
Requires-Dist: jinja2 (>=3.1,<4.0)
Project-URL: Repository, https://github.com/TheoGuerin64/taipan
